[
{ "number": 1, "arabic_name": "الفاتحة", "english_transliteration": "Al-Fatiha", "english_translation": "The Opener", "type": "Meccan", "total_verses": 7 },
{ "number": 2, "arabic_name": "البقرة", "english_transliteration": "Al-Baqarah", "english_translation": "The Cow", "type": "Medinan", "total_verses": 286 },
{ "number": 3, "arabic_name": "آل عمران", "english_transliteration": "Al-Imran", "english_translation": "Family of Imran", "type": "Medinan", "total_verses": 200 },
{ "number": 4, "arabic_name": "النساء", "english_transliteration": "An-Nisa", "english_translation": "The Women", "type": "Medinan", "total_verses": 176 },
{ "number": 5, "arabic_name": "المائدة", "english_transliteration": "Al-Ma'idah", "english_translation": "The Table Spread", "type": "Medinan", "total_verses": 120 },
{ "number": 6, "arabic_name": "الأنعام", "english_transliteration": "Al-An'am", "english_translation": "The Cattle", "type": "Meccan", "total_verses": 165 },
{ "number": 7, "arabic_name": "الأعراف", "english_transliteration": "Al-A'raf", "english_translation": "The Heights", "type": "Meccan", "total_verses": 206 },
{ "number": 8, "arabic_name": "الأنفال", "english_transliteration": "Al-Anfal", "english_translation": "The Spoils of War", "type": "Medinan", "total_verses": 75 },
{ "number": 9, "arabic_name": "التوبة", "english_transliteration": "At-Tawbah", "english_translation": "The Repentance", "type": "Medinan", "total_verses": 129 },
{ "number": 10, "arabic_name": "يونس", "english_transliteration": "Yunus", "english_translation": "Jonah", "type": "Meccan", "total_verses": 109 },
{ "number": 11, "arabic_name": "هود", "english_transliteration": "Hud", "english_translation": "Hud", "type": "Meccan", "total_verses": 123 },
{ "number": 12, "arabic_name": "يوسف", "english_transliteration": "Yusuf", "english_translation": "Joseph", "type": "Meccan", "total_verses": 111 },
{ "number": 13, "arabic_name": "الرعد", "english_transliteration": "Ar-Ra'd", "english_translation": "The Thunder", "type": "Medinan", "total_verses": 43 },
{ "number": 14, "arabic_name": "إبراهيم", "english_transliteration": "Ibrahim", "english_translation": "Abraham", "type": "Meccan", "total_verses": 52 },
{ "number": 15, "arabic_name": "الحجر", "english_transliteration": "Al-Hijr", "english_translation": "The Rocky Tract", "type": "Meccan", "total_verses": 99 },
{ "number": 16, "arabic_name": "النحل", "english_transliteration": "An-Nahl", "english_translation": "The Bee", "type": "Meccan", "total_verses": 128 },
{ "number": 17, "arabic_name": "الإسراء", "english_transliteration": "Al-Isra", "english_translation": "The Night Journey", "type": "Meccan", "total_verses": 111 },
{ "number": 18, "arabic_name": "الكهف", "english_transliteration": "Al-Kahf", "english_translation": "The Cave", "type": "Meccan", "total_verses": 110 },
{ "number": 19, "arabic_name": "مريم", "english_transliteration": "Maryam", "english_translation": "Mary", "type": "Meccan", "total_verses": 98 },
{ "number": 20, "arabic_name": "طه", "english_transliteration": "Taha", "english_translation": "Ta-Ha", "type": "Meccan", "total_verses": 135 },
{ "number": 21, "arabic_name": "الأنبياء", "english_transliteration": "Al-Anbiya", "english_translation": "The Prophets", "type": "Meccan", "total_verses": 112 },
{ "number": 22, "arabic_name": "الحج", "english_transliteration": "Al-Hajj", "english_translation": "The Pilgrimage", "type": "Medinan", "total_verses": 78 },
{ "number": 23, "arabic_name": "المؤمنون", "english_transliteration": "Al-Mu'minun", "english_translation": "The Believers", "type": "Meccan", "total_verses": 118 },
{ "number": 24, "arabic_name": "النور", "english_transliteration": "An-Nur", "english_translation": "The Light", "type": "Medinan", "total_verses": 64 },
{ "number": 25, "arabic_name": "الفرقان", "english_transliteration": "Al-Furqan", "english_translation": "The Criterion", "type": "Meccan", "total_verses": 77 },
{ "number": 26, "arabic_name": "الشعراء", "english_transliteration": "Ash-Shu'ara", "english_translation": "The Poets", "type": "Meccan", "total_verses": 227 },
{ "number": 27, "arabic_name": "النمل", "english_transliteration": "An-Naml", "english_translation": "The Ant", "type": "Meccan", "total_verses": 93 },
{ "number": 28, "arabic_name": "القصص", "english_transliteration": "Al-Qasas", "english_translation": "The Stories", "type": "Meccan", "total_verses": 88 },
{ "number": 29, "arabic_name": "العنكبوت", "english_transliteration": "Al-'Ankabut", "english_translation": "The Spider", "type": "Meccan", "total_verses": 69 },
{ "number": 30, "arabic_name": "الروم", "english_transliteration": "Ar-Rum", "english_translation": "The Romans", "type": "Meccan", "total_verses": 60 },
{ "number": 31, "arabic_name": "لقمان", "english_transliteration": "Luqman", "english_translation": "Luqman", "type": "Meccan", "total_verses": 34 },
{ "number": 32, "arabic_name": "السجدة", "english_transliteration": "As-Sajdah", "english_translation": "The Prostration", "type": "Meccan", "total_verses": 30 },
{ "number": 33, "arabic_name": "الأحزاب", "english_transliteration": "Al-Ahzab", "english_translation": "The Clans", "type": "Medinan", "total_verses": 73 },
{ "number": 34, "arabic_name": "سبأ", "english_transliteration": "Saba", "english_translation": "Sheba", "type": "Meccan", "total_verses": 54 },
{ "number": 35, "arabic_name": "فاطر", "english_transliteration": "Fatir", "english_translation": "The Originator", "type": "Meccan", "total_verses": 45 },
{ "number": 36, "arabic_name": "يس", "english_transliteration": "Ya-Sin", "english_translation": "Ya-Sin", "type": "Meccan", "total_verses": 83 },
{ "number": 37, "arabic_name": "الصافات", "english_transliteration": "As-Saffat", "english_translation": "Those Who Set The Ranks", "type": "Meccan", "total_verses": 182 },
{ "number": 38, "arabic_name": "ص", "english_transliteration": "Sad", "english_translation": "Sad", "type": "Meccan", "total_verses": 88 },
{ "number": 39, "arabic_name": "الزمر", "english_transliteration": "Az-Zumar", "english_translation": "The Troops", "type": "Meccan", "total_verses": 75 },
{ "number": 40, "arabic_name": "غافر", "english_transliteration": "Ghafir", "english_translation": "The Forgiver", "type": "Meccan", "total_verses": 85 },
{ "number": 41, "arabic_name": "فصلت", "english_transliteration": "Fussilat", "english_translation": "Explained In Detail", "type": "Meccan", "total_verses": 54 },
{ "number": 42, "arabic_name": "الشورى", "english_transliteration": "Ash-Shura", "english_translation": "The Consultation", "type": "Meccan", "total_verses": 53 },
{ "number": 43, "arabic_name": "الزخرف", "english_transliteration": "Az-Zukhruf", "english_translation": "The Gold Adornments", "type": "Meccan", "total_verses": 89 },
{ "number": 44, "arabic_name": "الدخان", "english_transliteration": "Ad-Dukhan", "english_translation": "The Smoke", "type": "Meccan", "total_verses": 59 },
{ "number": 45, "arabic_name": "الجاثية", "english_transliteration": "Al-Jathiyah", "english_translation": "The Kneeling", "type": "Meccan", "total_verses": 37 },
{ "number": 46, "arabic_name": "الأحقاف", "english_transliteration": "Al-Ahqaf", "english_translation": "The Wind-Curved Sandhills", "type": "Meccan", "total_verses": 35 },
{ "number": 47, "arabic_name": "محمد", "english_transliteration": "Muhammad", "english_translation": "Muhammad", "type": "Medinan", "total_verses": 38 },
{ "number": 48, "arabic_name": "الفتح", "english_transliteration": "Al-Fath", "english_translation": "The Victory", "type": "Medinan", "total_verses": 29 },
{ "number": 49, "arabic_name": "الحجرات", "english_transliteration": "Al-Hujurat", "english_translation": "The Rooms", "type": "Medinan", "total_verses": 18 },
{ "number": 50, "arabic_name": "ق", "english_transliteration": "Qaf", "english_translation": "Qaf", "type": "Meccan", "total_verses": 45 },
{ "number": 51, "arabic_name": "الذاريات", "english_transliteration": "Adh-Dhariyat", "english_translation": "The Winnowing Winds", "type": "Meccan", "total_verses": 60 },
{ "number": 52, "arabic_name": "الطور", "english_transliteration": "At-Tur", "english_translation": "The Mount", "type": "Meccan", "total_verses": 49 },
{ "number": 53, "arabic_name": "النجم", "english_transliteration": "An-Najm", "english_translation": "The Star", "type": "Meccan", "total_verses": 62 },
{ "number": 54, "arabic_name": "القمر", "english_transliteration": "Al-Qamar", "english_translation": "The Moon", "type": "Meccan", "total_verses": 55 },
{ "number": 55, "arabic_name": "الرحمن", "english_transliteration": "Ar-Rahman", "english_translation": "The Beneficent", "type": "Medinan", "total_verses": 78 },
{ "number": 56, "arabic_name": "الواقعة", "english_transliteration": "Al-Waqi'ah", "english_translation": "The Event", "type": "Meccan", "total_verses": 96 },
{ "number": 57, "arabic_name": "الحديد", "english_transliteration": "Al-Hadid", "english_translation": "The Iron", "type": "Medinan", "total_verses": 29 },
{ "number": 58, "arabic_name": "المجادلة", "english_transliteration": "Al-Mujadila", "english_translation": "The Pleading Woman", "type": "Medinan", "total_verses": 22 },
{ "number": 59, "arabic_name": "الحشر", "english_transliteration": "Al-Hashr", "english_translation": "The Exile", "type": "Medinan", "total_verses": 24 },
{ "number": 60, "arabic_name": "الممتحنة", "english_transliteration": "Al-Mumtahanah", "english_translation": "She That Is To Be Examined", "type": "Medinan", "total_verses": 13 },
{ "number": 61, "arabic_name": "الصف", "english_transliteration": "As-Saff", "english_translation": "The Ranks", "type": "Medinan", "total_verses": 14 },
{ "number": 62, "arabic_name": "الجمعة", "english_transliteration": "Al-Jumu'ah", "english_translation": "The Congregation (Friday) Prayer", "type": "Medinan", "total_verses": 11 },
{ "number": 63, "arabic_name": "المنافقون", "english_transliteration": "Al-Munafiqun", "english_translation": "The Hypocrites", "type": "Medinan", "total_verses": 11 },
{ "number": 64, "arabic_name": "التغابن", "english_transliteration": "At-Taghabun", "english_translation": "Mutual Disillusion", "type": "Medinan", "total_verses": 18 },
{ "number": 65, "arabic_name": "الطلاق", "english_transliteration": "At-Talaq", "english_translation": "The Divorce", "type": "Medinan", "total_verses": 12 },
{ "number": 66, "arabic_name": "التحريم", "english_transliteration": "At-Tahrim", "english_translation": "The Prohibition", "type": "Medinan", "total_verses": 12 },
{ "number": 67, "arabic_name": "الملك", "english_transliteration": "Al-Mulk", "english_translation": "The Sovereignty", "type": "Meccan", "total_verses": 30 },
{ "number": 68, "arabic_name": "القلم", "english_transliteration": "Al-Qalam", "english_translation": "The Pen", "type": "Meccan", "total_verses": 52 },
{ "number": 69, "arabic_name": "الحاقة", "english_transliteration": "Al-Haqqah", "english_translation": "The Reality", "type": "Meccan", "total_verses": 52 },
{ "number": 70, "arabic_name": "المعارج", "english_transliteration": "Al-Ma'arij", "english_translation": "The Ascending Stairways", "type": "Meccan", "total_verses": 44 },
{ "number": 71, "arabic_name": "نوح", "english_transliteration": "Nuh", "english_translation": "Noah", "type": "Meccan", "total_verses": 28 },
{ "number": 72, "arabic_name": "الجن", "english_transliteration": "Al-Jinn", "english_translation": "The Jinn", "type": "Meccan", "total_verses": 28 },
{ "number": 73, "arabic_name": "المزمل", "english_transliteration": "Al-Muzzammil", "english_translation": "The Enshrouded One", "type": "Meccan", "total_verses": 20 },
{ "number": 74, "arabic_name": "المدثر", "english_transliteration": "Al-Muddaththir", "english_translation": "The Cloaked One", "type": "Meccan", "total_verses": 56 },
{ "number": 75, "arabic_name": "القيامة", "english_transliteration": "Al-Qiyamah", "english_translation": "The Resurrection", "type": "Meccan", "total_verses": 40 },
{ "number": 76, "arabic_name": "الإنسان", "english_transliteration": "Al-Insan", "english_translation": "The Man", "type": "Medinan", "total_verses": 31 },
{ "number": 77, "arabic_name": "المرسلات", "english_transliteration": "Al-Mursalat", "english_translation": "The Emissaries", "type": "Meccan", "total_verses": 50 },
{ "number": 78, "arabic_name": "النبأ", "english_transliteration": "An-Naba", "english_translation": "The Tidings", "type": "Meccan", "total_verses": 40 },
{ "number": 79, "arabic_name": "النازعات", "english_transliteration": "An-Nazi'at", "english_translation": "Those Who Drag Forth", "type": "Meccan", "total_verses": 46 },
{ "number": 80, "arabic_name": "عبس", "english_transliteration": "'Abasa", "english_translation": "He Frowned", "type": "Meccan", "total_verses": 42 },
{ "number": 81, "arabic_name": "التكوير", "english_transliteration": "At-Takwir", "english_translation": "The Overthrowing", "type": "Meccan", "total_verses": 29 },
{ "number": 82, "arabic_name": "الإنفطار", "english_transliteration": "Al-Infitar", "english_translation": "The Cleaving", "type": "Meccan", "total_verses": 19 },
{ "number": 83, "arabic_name": "المطففين", "english_transliteration": "Al-Mutaffifin", "english_translation": "The Defrauding", "type": "Meccan", "total_verses": 36 },
{ "number": 84, "arabic_name": "الإنشقاق", "english_transliteration": "Al-Inshiqaq", "english_translation": "The Sundering", "type": "Meccan", "total_verses": 25 },
{ "number": 85, "arabic_name": "البروج", "english_transliteration": "Al-Buruj", "english_translation": "The Mansions of the Stars", "type": "Meccan", "total_verses": 22 },
{ "number": 86, "arabic_name": "الطارق", "english_transliteration": "At-Tariq", "english_translation": "The Nightcommer", "type": "Meccan", "total_verses": 17 },
{ "number": 87, "arabic_name": "الأعلى", "english_transliteration": "Al-A'la", "english_translation": "The Most High", "type": "Meccan", "total_verses": 19 },
{ "number": 88, "arabic_name": "الغاشية", "english_transliteration": "Al-Ghashiyah", "english_translation": "The Overwhelming", "type": "Meccan", "total_verses": 26 },
{ "number": 89, "arabic_name": "الفجر", "english_transliteration": "Al-Fajr", "english_translation": "The Dawn", "type": "Meccan", "total_verses": 30 },
{ "number": 90, "arabic_name": "البلد", "english_transliteration": "Al-Balad", "english_translation": "The City", "type": "Meccan", "total_verses": 20 },
{ "number": 91, "arabic_name": "الشمس", "english_transliteration": "Ash-Shams", "english_translation": "The Sun", "type": "Meccan", "total_verses": 15 },
{ "number": 92, "arabic_name": "الليل", "english_transliteration": "Al-Layl", "english_translation": "The Night", "type": "Meccan", "total_verses": 21 },
{ "number": 93, "arabic_name": "الضحى", "english_transliteration": "Ad-Duha", "english_translation": "The Morning Hours", "type": "Meccan", "total_verses": 11 },
{ "number": 94, "arabic_name": "الشرح", "english_transliteration": "Ash-Sharh", "english_translation": "The Relief", "type": "Meccan", "total_verses": 8 },
{ "number": 95, "arabic_name": "التين", "english_transliteration": "At-Tin", "english_translation": "The Fig", "type": "Meccan", "total_verses": 8 },
{ "number": 96, "arabic_name": "العلق", "english_transliteration": "Al-Alaq", "english_translation": "The Clot", "type": "Meccan", "total_verses": 19 },
{ "number": 97, "arabic_name": "القدر", "english_transliteration": "Al-Qadr", "english_translation": "The Power", "type": "Meccan", "total_verses": 5 },
{ "number": 98, "arabic_name": "البينة", "english_transliteration": "Al-Bayyinah", "english_translation": "The Clear Proof", "type": "Medinan", "total_verses": 8 },
{ "number": 99, "arabic_name": "الزلزلة", "english_transliteration": "Az-Zalzalah", "english_translation": "The Earthquake", "type": "Medinan", "total_verses": 8 },
{ "number": 100, "arabic_name": "العاديات", "english_transliteration": "Al-'Adiyat", "english_translation": "The Courser", "type": "Meccan", "total_verses": 11 },
{ "number": 101, "arabic_name": "القارعة", "english_transliteration": "Al-Qari'ah", "english_translation": "The Calamity", "type": "Meccan", "total_verses": 11 },
{ "number": 102, "arabic_name": "التكاثر", "english_transliteration": "At-Takathur", "english_translation": "The Rivalry In Worldly Increase", "type": "Meccan", "total_verses": 8 },
{ "number": 103, "arabic_name": "العصر", "english_transliteration": "Al-Asr", "english_translation": "The Declining Day", "type": "Meccan", "total_verses": 3 },
{ "number": 104, "arabic_name": "الهمزة", "english_transliteration": "Al-Humazah", "english_translation": "The Traducer", "type": "Meccan", "total_verses": 9 },
{ "number": 105, "arabic_name": "الفيل", "english_transliteration": "Al-Fil", "english_translation": "The Elephant", "type": "Meccan", "total_verses": 5 },
{ "number": 106, "arabic_name": "قريش", "english_transliteration": "Quraish", "english_translation": "Quraish", "type": "Meccan", "total_verses": 4 },
{ "number": 107, "arabic_name": "الماعون", "english_transliteration": "Al-Ma'un", "english_translation": "The Small Kindnesses", "type": "Meccan", "total_verses": 7 },
{ "number": 108, "arabic_name": "الكوثر", "english_transliteration": "Al-Kawthar", "english_translation": "The Abundance", "type": "Meccan", "total_verses": 3 },
{ "number": 109, "arabic_name": "الكافرون", "english_transliteration": "Al-Kafirun", "english_translation": "The Disbelievers", "type": "Meccan", "total_verses": 6 },
{ "number": 110, "arabic_name": "النصر", "english_transliteration": "An-Nasr", "english_translation": "The Divine Support", "type": "Medinan", "total_verses": 3 },
{ "number": 111, "arabic_name": "المسد", "english_transliteration": "Al-Masad", "english_translation": "The Palm Fiber", "type": "Meccan", "total_verses": 5 },
{ "number": 112, "arabic_name": "الإخلاص", "english_transliteration": "Al-Ikhlas", "english_translation": "The Sincerity", "type": "Meccan", "total_verses": 4 },
{ "number": 113, "arabic_name": "الفلق", "english_transliteration": "Al-Falaq", "english_translation": "The Daybreak", "type": "Meccan", "total_verses": 5 },
{ "number": 114, "arabic_name": "الناس", "english_transliteration": "An-Nas", "english_translation": "Mankind", "type": "Meccan", "total_verses": 6 }
]